kailash/__init__.py
kailash/__main__.py
kailash/access_control.py
kailash/access_control_abac.py
kailash/manifest.py
kailash/sdk_exceptions.py
kailash/security.py
kailash/access_control/__init__.py
kailash/access_control/managers.py
kailash/access_control/rule_evaluators.py
kailash/adapters/__init__.py
kailash/adapters/mcp_platform_adapter.py
kailash/analysis/__init__.py
kailash/analysis/conditional_branch_analyzer.py
kailash/api/auth.py
kailash/api/custom_nodes.py
kailash/api/custom_nodes_secure.py
kailash/api/gateway.py
kailash/api/mcp_integration.py
kailash/api/studio.py
kailash/api/workflow_api.py
kailash/api/tests/test_workflow_api_404.py
kailash/channels/__init__.py
kailash/channels/api_channel.py
kailash/channels/base.py
kailash/channels/cli_channel.py
kailash/channels/event_router.py
kailash/channels/mcp_channel.py
kailash/channels/session.py
kailash/cli/__init__.py
kailash/cli/commands.py
kailash/cli/validate_imports.py
kailash/cli/validation_audit.py
kailash/client/__init__.py
kailash/client/enhanced_client.py
kailash/config/__init__.py
kailash/config/database_config.py
kailash/core/actors/__init__.py
kailash/core/actors/adaptive_pool_controller.py
kailash/core/actors/connection_actor.py
kailash/core/actors/supervisor.py
kailash/core/ml/__init__.py
kailash/core/ml/query_patterns.py
kailash/core/monitoring/__init__.py
kailash/core/monitoring/connection_metrics.py
kailash/core/optimization/__init__.py
kailash/core/resilience/__init__.py
kailash/core/resilience/bulkhead.py
kailash/core/resilience/circuit_breaker.py
kailash/core/resilience/health_monitor.py
kailash/database/__init__.py
kailash/database/execution_pipeline.py
kailash/edge/__init__.py
kailash/edge/compliance.py
kailash/edge/consistency.py
kailash/edge/discovery.py
kailash/edge/location.py
kailash/edge/coordination/__init__.py
kailash/edge/coordination/global_ordering.py
kailash/edge/coordination/leader_election.py
kailash/edge/coordination/partition_detector.py
kailash/edge/coordination/raft.py
kailash-0.10.16.dist-info/licenses/LICENSE
kailash-0.10.16.dist-info/licenses/NOTICE
kailash-0.10.16.dist-info/METADATA
kailash-0.10.16.dist-info/WHEEL
kailash-0.10.16.dist-info/entry_points.txt
kailash-0.10.16.dist-info/top_level.txt
kailash-0.10.16.dist-info/RECORD
