Metadata-Version: 2.4
Name: kailash
Version: 0.10.16
Summary: Python SDK for the Kailash container-node architecture
Home-page: https://github.com/integrum/kailash-python-sdk
Author: Integrum
Author-email: Integrum <info@integrum.com>
License: Apache-2.0 WITH Additional-Terms
Project-URL: Homepage, https://github.com/integrum/kailash-python-sdk
Project-URL: Bug Tracker, https://github.com/integrum/kailash-python-sdk/issues
Project-URL: License, https://github.com/integrum/kailash-python-sdk/blob/main/LICENSE
Classifier: Development Status :: 3 - Alpha
Classifier: Intended Audience :: Developers
Classifier: License :: OSI Approved :: Apache Software License
Classifier: Programming Language :: Python :: 3
Classifier: Programming Language :: Python :: 3.11
Classifier: Programming Language :: Python :: 3.12
Classifier: Programming Language :: Python :: 3.13
Requires-Python: >=3.11
License-File: LICENSE
License-File: NOTICE
Requires-Dist: networkx>=2.7
Requires-Dist: pydantic>=1.9
Requires-Dist: matplotlib>=3.5
Requires-Dist: pyyaml>=6.0
Requires-Dist: click>=8.0
Requires-Dist: pytest>=8.3.5
Requires-Dist: mcp[cli]<2.0,>=1.23.0
Requires-Dist: pandas>=2.2.3
Requires-Dist: numpy>=2.2.5
Requires-Dist: scipy>=1.15.3
Requires-Dist: scikit-learn>=1.6.1
Requires-Dist: requests>=2.32.3
Requires-Dist: pytest-cov>=6.1.1
Requires-Dist: isort>=6.0.1
Requires-Dist: aiohttp>=3.12.4
Requires-Dist: aiohttp-cors>=0.7.0
Requires-Dist: ruff>=0.11.12
Requires-Dist: msal>=1.32.3
Requires-Dist: sphinx>=8.2.3
Requires-Dist: sphinx-rtd-theme>=3.0.2
Requires-Dist: sphinx-copybutton>=0.5.2
Requires-Dist: sphinxcontrib-mermaid>=1.0.0
Requires-Dist: sphinx-autobuild>=2024.10.3
Requires-Dist: autodoc>=0.5.0
Requires-Dist: myst-parser>=4.0.1
Requires-Dist: black>=25.1.0
Requires-Dist: psutil>=7.0.0
Requires-Dist: fastapi>=0.115.12
Requires-Dist: uvicorn[standard]>=0.31.0
Requires-Dist: pytest-asyncio>=1.0.0
Requires-Dist: pre-commit>=4.2.0
Requires-Dist: twine>=6.1.0
Requires-Dist: ollama>=0.5.1
Requires-Dist: sqlalchemy>=2.0.0
Requires-Dist: pymysql>=1.1.0
Requires-Dist: aiosqlite>=0.19.0
Requires-Dist: websockets>=12.0
Requires-Dist: httpx>=0.25.0
Requires-Dist: python-jose[cryptography]>=3.5.0
Requires-Dist: pytest-xdist>=3.6.0
Requires-Dist: pytest-timeout>=2.3.0
Requires-Dist: pytest-split>=0.9.0
Requires-Dist: asyncpg>=0.30.0
Requires-Dist: aiomysql>=0.2.0
Requires-Dist: twilio>=9.6.3
Requires-Dist: qrcode>=8.2
Requires-Dist: aiofiles>=24.1.0
Requires-Dist: bcrypt>=4.3.0
Requires-Dist: plotly>=6.2.0
Requires-Dist: redis>=6.2.0
Requires-Dist: faker>=37.4.0
Requires-Dist: structlog>=25.4.0
Requires-Dist: authlib>=1.6.0
Requires-Dist: slowapi>=0.1.9
Requires-Dist: limits>=5.4.0
Requires-Dist: prometheus-client>=0.22.1
Requires-Dist: opentelemetry-api>=1.34.1
Requires-Dist: opentelemetry-sdk>=1.34.1
Requires-Dist: passlib>=1.7.4
Requires-Dist: pyotp>=2.9.0
Requires-Dist: opentelemetry-instrumentation-fastapi>=0.55b1
Requires-Dist: seaborn>=0.13.2
Requires-Dist: sqlparse>=0.5.3
Requires-Dist: jsonschema>=4.24.0
Requires-Dist: openai>=1.97.1
Requires-Dist: pymongo>=4.15.2
Requires-Dist: psycopg>=3.2.10
Provides-Extra: dev
Requires-Dist: pytest>=7.0; extra == "dev"
Requires-Dist: pytest-cov>=3.0; extra == "dev"
Requires-Dist: black>=22.0; extra == "dev"
Requires-Dist: isort>=5.10; extra == "dev"
Requires-Dist: mypy>=0.9; extra == "dev"
Dynamic: author
Dynamic: home-page
Dynamic: license-file
Dynamic: requires-python
